pypresto/__init__.py
pypresto/connection.py
pypresto-1.0.4.dist-info/DESCRIPTION.rst
pypresto-1.0.4.dist-info/METADATA
pypresto-1.0.4.dist-info/RECORD
pypresto-1.0.4.dist-info/WHEEL
pypresto-1.0.4.dist-info/metadata.json
pypresto-1.0.4.dist-info/top_level.txt
