Metadata-Version: 2.0
Name: pypresto
Version: 1.0.4
Summary: Python wrapper for running queries on Presto server
Home-page: https://github.com/NonWhite/pyprestowrapper
Author: NonWhite
Author-email: wperezurcia@gmail.com
License: LICENSE
Platform: UNKNOWN
Classifier: Programming Language :: Python :: 2.7
Classifier: Development Status :: 4 - Beta
Requires-Dist: pandas (==0.20.3)
Requires-Dist: requests (==2.18.4)
